<?xml version="1.0" encoding="UTF-8"?>
<feature
      id="org.eclipse.jdt.feature.patch"
      label="Eclipse JDT Patch to Enable Eclipse Testing Two Zero"
      version="0.5.3"
      provider-name="Chocolate Jar">

   <description url="http://www.example.com/description">
      [Enter Feature Description here.]
   </description>

   <copyright url="http://www.example.com/copyright">
      [Enter Copyright Description here.]
   </copyright>

   <license url="http://www.example.com/license">
      [Enter License Description here.]
   </license>

   <requires>
      <import feature="org.eclipse.jdt" version="3.9.1.v20130911-1000" patch="true"/>
   </requires>

   <plugin
         id="org.eclipse.jdt.junit"
         download-size="0"
         install-size="0"
         version="0.0.0"
         unpack="false"/>

   <plugin
         id="org.eclipse.jdt.junit.core"
         download-size="0"
         install-size="0"
         version="0.0.0"
         unpack="false"/>

   <plugin
         id="org.eclipse.jdt.junit.runtime"
         download-size="0"
         install-size="0"
         version="0.0.0"
         unpack="false"/>

   <plugin
         id="org.eclipse.jdt.junit4.runtime"
         download-size="0"
         install-size="0"
         version="0.0.0"
         unpack="false"/>

</feature>
